{
  "hyperparameters": {
    "epochs_daily": 25,
    "epochs_hourly": 30,
    "epochs_execution": 15,
    "batch_daily": 32,
    "batch_hourly": 64,
    "batch_execution": 128,
    "lr_daily": 0.001,
    "lr_hourly": 0.0005,
    "lr_execution": 0.001,
    "seq_daily": 45,
    "seq_hourly": 24,
    "seq_execution": 24,
    "val_ratio": 0.2,
    "dropout": 0.1
  },
  "daily": {
    "best_val_loss": 1.0784969470883143,
    "best_val_accuracy": 0.4122137404580153,
    "eval_loss": 1.1574713219213122,
    "eval_accuracy": 0.366412213740458,
    "history": [
      {
        "epoch": 1,
        "train_loss": 1.1376112551916213,
        "val_loss": 1.1173009936136145,
        "val_acc": 0.3893129770992366
      },
      {
        "epoch": 2,
        "train_loss": 1.1155754189264206,
        "val_loss": 1.0908549550835414,
        "val_acc": 0.3893129770992366
      },
      {
        "epoch": 3,
        "train_loss": 1.107592504819234,
        "val_loss": 1.0873274047866122,
        "val_acc": 0.3816793893129771
      },
      {
        "epoch": 4,
        "train_loss": 1.109061355363755,
        "val_loss": 1.141633294920885,
        "val_acc": 0.32061068702290074
      },
      {
        "epoch": 5,
        "train_loss": 1.0927705746605283,
        "val_loss": 1.0920624764821,
        "val_acc": 0.3816793893129771
      },
      {
        "epoch": 6,
        "train_loss": 1.097741169021243,
        "val_loss": 1.1038425068818887,
        "val_acc": 0.40458015267175573
      },
      {
        "epoch": 7,
        "train_loss": 1.0995245411282495,
        "val_loss": 1.1281561596702983,
        "val_acc": 0.3969465648854962
      },
      {
        "epoch": 8,
        "train_loss": 1.0940754363650367,
        "val_loss": 1.0824158091581504,
        "val_acc": 0.42748091603053434
      },
      {
        "epoch": 9,
        "train_loss": 1.0899687671661378,
        "val_loss": 1.1038341745165468,
        "val_acc": 0.45038167938931295
      },
      {
        "epoch": 10,
        "train_loss": 1.0678084303083875,
        "val_loss": 1.0784969470883143,
        "val_acc": 0.4122137404580153
      },
      {
        "epoch": 11,
        "train_loss": 1.0928337893031892,
        "val_loss": 1.1208581228292624,
        "val_acc": 0.4122137404580153
      },
      {
        "epoch": 12,
        "train_loss": 1.074145070257641,
        "val_loss": 1.1028928961462647,
        "val_acc": 0.44274809160305345
      },
      {
        "epoch": 13,
        "train_loss": 1.0699828933534168,
        "val_loss": 1.0931524793610319,
        "val_acc": 0.40458015267175573
      },
      {
        "epoch": 14,
        "train_loss": 1.0618435212544033,
        "val_loss": 1.093077150464968,
        "val_acc": 0.42748091603053434
      },
      {
        "epoch": 15,
        "train_loss": 1.0586931396666028,
        "val_loss": 1.0995060255509297,
        "val_acc": 0.4351145038167939
      },
      {
        "epoch": 16,
        "train_loss": 1.0620625534511747,
        "val_loss": 1.104682052408466,
        "val_acc": 0.3816793893129771
      },
      {
        "epoch": 17,
        "train_loss": 1.0401698135194324,
        "val_loss": 1.1045117446484456,
        "val_acc": 0.4122137404580153
      },
      {
        "epoch": 18,
        "train_loss": 1.0091253910745894,
        "val_loss": 1.171796613067161,
        "val_acc": 0.40458015267175573
      },
      {
        "epoch": 19,
        "train_loss": 1.0181764981860206,
        "val_loss": 1.1584548449698295,
        "val_acc": 0.35877862595419846
      },
      {
        "epoch": 20,
        "train_loss": 1.0275999053319296,
        "val_loss": 1.1192058470412976,
        "val_acc": 0.4122137404580153
      },
      {
        "epoch": 21,
        "train_loss": 0.9939156627655029,
        "val_loss": 1.1647581690140354,
        "val_acc": 0.4198473282442748
      },
      {
        "epoch": 22,
        "train_loss": 0.9861391335441952,
        "val_loss": 1.203691314649946,
        "val_acc": 0.3511450381679389
      },
      {
        "epoch": 23,
        "train_loss": 0.9889231777191162,
        "val_loss": 1.174701988697052,
        "val_acc": 0.3969465648854962
      },
      {
        "epoch": 24,
        "train_loss": 0.9735933291344415,
        "val_loss": 1.1992677800527967,
        "val_acc": 0.3511450381679389
      },
      {
        "epoch": 25,
        "train_loss": 0.9529763588451203,
        "val_loss": 1.1574713219213122,
        "val_acc": 0.366412213740458
      }
    ],
    "train_samples": 525,
    "val_samples": 131
  },
  "hourly": {
    "mse": 0.08511245905698,
    "mae": 0.0883430268738296,
    "best_val_loss": 0.02624316321815545,
    "history": [
      {
        "epoch": 1,
        "train_loss": 0.19126985487706918,
        "val_loss": 0.048917692864225024
      },
      {
        "epoch": 2,
        "train_loss": 0.10278401600105017,
        "val_loss": 0.03840613516641187
      },
      {
        "epoch": 3,
        "train_loss": 0.08541981232994435,
        "val_loss": 0.029023045134959204
      },
      {
        "epoch": 4,
        "train_loss": 0.07248742863454156,
        "val_loss": 0.02935611289472152
      },
      {
        "epoch": 5,
        "train_loss": 0.06477200513674965,
        "val_loss": 0.028047498370155747
      },
      {
        "epoch": 6,
        "train_loss": 0.06113814134184795,
        "val_loss": 0.027255231951237163
      },
      {
        "epoch": 7,
        "train_loss": 0.05604141027797729,
        "val_loss": 0.027824030684191228
      },
      {
        "epoch": 8,
        "train_loss": 0.05259440580495315,
        "val_loss": 0.02687420073091547
      },
      {
        "epoch": 9,
        "train_loss": 0.04834303865975392,
        "val_loss": 0.02948459776821154
      },
      {
        "epoch": 10,
        "train_loss": 0.04761983181811338,
        "val_loss": 0.02708509325599059
      },
      {
        "epoch": 11,
        "train_loss": 0.044252435239185144,
        "val_loss": 0.027281113480637362
      },
      {
        "epoch": 12,
        "train_loss": 0.04348059935015124,
        "val_loss": 0.027605686452744645
      },
      {
        "epoch": 13,
        "train_loss": 0.04148334198694342,
        "val_loss": 0.02676593109064705
      },
      {
        "epoch": 14,
        "train_loss": 0.03994133003682607,
        "val_loss": 0.02837948323715301
      },
      {
        "epoch": 15,
        "train_loss": 0.04174557434466465,
        "val_loss": 0.03084960155489244
      },
      {
        "epoch": 16,
        "train_loss": 0.03997294443201485,
        "val_loss": 0.027375912982902248
      },
      {
        "epoch": 17,
        "train_loss": 0.03864384318448236,
        "val_loss": 0.02860870636017113
      },
      {
        "epoch": 18,
        "train_loss": 0.03877640605463188,
        "val_loss": 0.026845885577164726
      },
      {
        "epoch": 19,
        "train_loss": 0.03672208320315403,
        "val_loss": 0.02624316321815545
      },
      {
        "epoch": 20,
        "train_loss": 0.036821316471374446,
        "val_loss": 0.027191881492952288
      },
      {
        "epoch": 21,
        "train_loss": 0.03586596424880368,
        "val_loss": 0.026368661432257502
      },
      {
        "epoch": 22,
        "train_loss": 0.03582863209656758,
        "val_loss": 0.027320787030862364
      },
      {
        "epoch": 23,
        "train_loss": 0.03644132221856544,
        "val_loss": 0.026718091069560346
      },
      {
        "epoch": 24,
        "train_loss": 0.03591655540046788,
        "val_loss": 0.026526767685463578
      },
      {
        "epoch": 25,
        "train_loss": 0.03559898294957944,
        "val_loss": 0.028968435463123707
      },
      {
        "epoch": 26,
        "train_loss": 0.036377405090567395,
        "val_loss": 0.026569209269660735
      },
      {
        "epoch": 27,
        "train_loss": 0.03503343428551497,
        "val_loss": 0.026604694256306568
      },
      {
        "epoch": 28,
        "train_loss": 0.035004511860350807,
        "val_loss": 0.0268124839318268
      },
      {
        "epoch": 29,
        "train_loss": 0.03622517928862484,
        "val_loss": 0.026344048319855234
      },
      {
        "epoch": 30,
        "train_loss": 0.03422796811356841,
        "val_loss": 0.028370820893309057
      }
    ],
    "train_samples": 1094,
    "val_samples": 273
  },
  "execution": {
    "mse": 0.0805760329459613,
    "mae": 0.08472304291777559,
    "best_val_loss": 0.026858678565193445,
    "history": [
      {
        "epoch": 1,
        "train_loss": 0.07137383872019962,
        "val_loss": 0.04439099195785138
      },
      {
        "epoch": 2,
        "train_loss": 0.04357107687857295,
        "val_loss": 0.02951124054635619
      },
      {
        "epoch": 3,
        "train_loss": 0.03656193852370138,
        "val_loss": 0.03724657389379683
      },
      {
        "epoch": 4,
        "train_loss": 0.03645381306926337,
        "val_loss": 0.03199428203942138
      },
      {
        "epoch": 5,
        "train_loss": 0.03305740160714338,
        "val_loss": 0.028828976982897454
      },
      {
        "epoch": 6,
        "train_loss": 0.0322769739115151,
        "val_loss": 0.029262946222673406
      },
      {
        "epoch": 7,
        "train_loss": 0.03129011563193972,
        "val_loss": 0.027985981860003627
      },
      {
        "epoch": 8,
        "train_loss": 0.03007973249749684,
        "val_loss": 0.028310636986360882
      },
      {
        "epoch": 9,
        "train_loss": 0.028987653366199795,
        "val_loss": 0.0274675947924455
      },
      {
        "epoch": 10,
        "train_loss": 0.028858191083428845,
        "val_loss": 0.027211677890284593
      },
      {
        "epoch": 11,
        "train_loss": 0.02785405606862287,
        "val_loss": 0.02726516668640432
      },
      {
        "epoch": 12,
        "train_loss": 0.027735839391866156,
        "val_loss": 0.027256242664796964
      },
      {
        "epoch": 13,
        "train_loss": 0.02674983916514752,
        "val_loss": 0.02708582153659819
      },
      {
        "epoch": 14,
        "train_loss": 0.02653511122236849,
        "val_loss": 0.02757809695961711
      },
      {
        "epoch": 15,
        "train_loss": 0.024985818062965133,
        "val_loss": 0.026858678565193445
      }
    ],
    "train_samples": 1094,
    "val_samples": 273
  }
}